{"_id": "GIGALITH", "number": "526", "ptuNumber": 251, "BaseStats": {"HP": 9, "Attack": 14, "Defense": 13, "Special Attack": 6, "Special Defense": 8, "Speed": 3}, "Type": ["Rock", "null"], "Abilities": {"Basic": ["Sturdy"], "Advanced": ["Sunglow", "Sand Force", "Solar Power"], "High": ["Sand Stream"]}, "Evolution": [[1, "Roggenrola", "Null", "Null"], [2, "Boldore", 25, "Null"], [3, "Gigalith", 40, "Null"]], "Height": 1.7, "SizeClass": "Large", "Weight": 260.0, "BreedingInformation": {"Gender Ratio": 50.0, "Egg Group": ["Mineral"], "Average Hatch Rate": -1}, "Diet": ["Terravore"], "Habitat": ["Cave", "Mountain"], "Capabilities": {"Overland": 5, "Sky": 0, "Swim": 3, "Levitate": 0, "Burrow": 0, "JumpH": 1, "JumpL": 1, "Power": 12, "WeightClass": "6", "Naturewalk": ["Cave", "Mountain"], "Other": []}, "LevelUpMoveList": [{"Level": 4, "Move": "Harden"}, {"Level": 7, "Move": "Sand Attack"}, {"Level": 10, "Move": "Headbutt"}, {"Level": 14, "Move": "Rock Blast"}, {"Level": 17, "Move": "Mud-Slap"}, {"Level": 20, "Move": "Iron Defense"}, {"Level": 23, "Move": "Smack Down"}, {"Level": 30, "Move": "Rock Slide"}, {"Level": 36, "Move": "Stealth Rock"}, {"Level": 42, "Move": "Sandstorm"}, {"Level": 48, "Move": "Stone Edge"}, {"Level": 55, "Move": "Explosion"}], "TMMoveList": ["06", "10", "15", "17", "21", "22", "23", "26", "27", "32", "37", "39", "42", "44", "45", "48", "64", "68", "69", "71", "78", "80", "87", "88", "90", "91", "96", "100"], "EggMoveList": [], "TutorMoveList": ["Block", "Earth Power", "Gravity", "Iron Defense", "Iron Head", "Laser Focus", "Power Gem (N)", "Snore", "Stealth Rock", "Stomping Tantrum", "Superpower", "Throat Chop"], "Skills": {"Athletics": {"Dice": 4, "Mod": 3}, "Acrobatics": {"Dice": 1, "Mod": 0}, "Combat": {"Dice": 4, "Mod": 0}, "Stealth": {"Dice": 2, "Mod": 0}, "Perception": {"Dice": 4, "Mod": 0}, "Focus": {"Dice": 5, "Mod": 2}}}