{"_id": "LAPRAS", "number": "131", "ptuNumber": 736, "Base Stats": {"HP": 13, "Attack": 9, "Defense": 8, "Special Attack": 9, "Special Defense": 10, "Speed": 6}, "Type": ["Water", "Ice"], "Abilities": {"Basic": ["Shell Armor", "Water Absorb"], "Advanced": ["Wistful Melody", "Wash Away"], "High": ["Hydration"]}, "Evolution": [[1, "Lapras", "Null", "Null"]], "Height": 2.5, "Size Class": "Large", "Weight": 220.0, "Breeding Information": {"Gender Ratio": 50.0, "Egg Group": ["Monster", "Water 1"], "Average Hatch Rate": 25}, "Diet": ["Omnivore"], "Habitat": ["Arctic", "Ocean"], "Capabilities": {"Overland": 2, "Sky": 0, "Swim": 10, "Levitate": 0, "Burrow": 0, "JumpH": 0, "JumpL": 0, "Power": 8, "WeightClass": "6", "Naturewalk": ["Ocean", "Tundra"], "Other": ["Fountain", "Gilled", "Mountable 2"]}, "Level Up Move List": [{"Level": 1, "Move": "Growl"}, {"Level": 1, "Move": "Sing"}, {"Level": 1, "Move": "Water Gun"}, {"Level": 4, "Move": "Mist"}, {"Level": 7, "Move": "Confuse Ray"}, {"Level": 10, "Move": "Ice Shard"}, {"Level": 14, "Move": "Water Pulse"}, {"Level": 18, "Move": "Body Slam"}, {"Level": 22, "Move": "Rain Dance"}, {"Level": 27, "Move": "Perish Song"}, {"Level": 32, "Move": "Ice Beam"}, {"Level": 37, "Move": "Brine"}, {"Level": 43, "Move": "Safeguard"}, {"Level": 47, "Move": "Hydro Pump"}, {"Level": 50, "Move": "Sheer Cold"}], "TM Move List": ["05", "06", "07", "10", "13", "14", "15", "17", "18", "20", "21", "24", "25", "27", "29", "32", "42", "44", "45", "48", "49", "67", "68", "78", "79", "85", "87", "88", "90", "94", "98", "100"], "Egg Move List": ["Ancient Power", "Avalanche", "Curse", "Dragon Dance", "Dragon Pulse", "Fissure", "Foresight", "Freeze-Dry", "Future Sight", "Horn Drill", "Refresh", "Tickle", "Whirlpool"], "Tutor Move List": ["Ancient Power", "Aqua Tail", "Avalanche", "Block", "Body Slam", "Dive", "Double-Edge", "Dragon Pulse", "Drill Run", "Heal Bell", "Hyper Voice", "Icy Wind", "Iron Head", "Iron Tail", "Outrage", "Shock Wave", "Signal Beam", "Snore", "Water Pulse", "Whirlpool", "Zen Headbutt"], "Skills": {"Athletics": {"Dice": 4, "Mod": 1}, "Acrobatics": {"Dice": 1, "Mod": 0}, "Combat": {"Dice": 3, "Mod": 0}, "Stealth": {"Dice": 2, "Mod": 0}, "Perception": {"Dice": 3, "Mod": 1}, "Focus": {"Dice": 4, "Mod": 0}}}