{"_id": "MORGREM", "number": "860", "ptuNumber": 97, "BaseStats": {"HP": 7, "Attack": 6, "Defense": 5, "Special Attack": 8, "Special Defense": 6, "Speed": 7}, "Type": ["Dark", "Fairy"], "Abilities": {"Basic": ["Frisk", "Decoy"], "Advanced": ["Pickpocket", "Weird Power"], "High": ["Prankster"]}, "Evolution": [[1, "Impidimp", "Null", "Null"], [2, "Morgrem", 20, "Null"], [3, "Grimmsnarl", 40, "Null"]], "Height": 0.8, "SizeClass": "Small", "Weight": 12.5, "BreedingInformation": {"Gender Ratio": 100.0, "Egg Group": ["Fairy", "Humanshape"], "Average Hatch Rate": -1}, "Diet": ["Nullivore"], "Habitat": ["Forest", "Urban"], "Capabilities": {"Overland": 6, "Sky": 0, "Swim": 4, "Levitate": 0, "Burrow": 0, "JumpH": 2, "JumpL": 2, "Power": 3, "WeightClass": "2", "Naturewalk": ["Forest"], "Other": ["Darkvision", "Stealth", "Underdog"]}, "LevelUpMoveList": [{"Level": "Evo", "Move": "False Surrender"}, {"Level": 4, "Move": "Bite"}, {"Level": 8, "Move": "Flatter"}, {"Level": 12, "Move": "Fake Tears"}, {"Level": 16, "Move": "Assurance"}, {"Level": 20, "Move": "Swagger"}, {"Level": 24, "Move": "Sucker Punch"}, {"Level": 28, "Move": "Torment"}, {"Level": 33, "Move": "Dark Pulse"}, {"Level": 40, "Move": "Nasty Plot"}, {"Level": 46, "Move": "Play Rough"}, {"Level": 52, "Move": "Foul Play"}], "TMMoveList": ["06", "10", "12", "16", "17", "21", "27", "28", "32", "33", "41", "42", "44", "45", "46", "48", "65", "73", "87", "88", "90", "97", "99", "100"], "EggMoveList": [], "TutorMoveList": ["Drain Punch", "Endure", "Foul Play", "Low Kick", "Mega Punch", "Mega Kick", "Metronome", "Snore", "Sucker Punch", "Throat Chop", "Trick", "Uproar"], "Skills": {"Athletics": {"Dice": 4, "Mod": 0}, "Acrobatics": {"Dice": 3, "Mod": 0}, "Combat": {"Dice": 3, "Mod": 1}, "Stealth": {"Dice": 4, "Mod": 1}, "Perception": {"Dice": 3, "Mod": 0}, "Focus": {"Dice": 4, "Mod": 0}}}