{"_id": "ORICORIO", "number": "741", "ptuNumber": 758, "BaseStats": {"HP": 8, "Attack": 7, "Defense": 7, "Special Attack": 10, "Special Defense": 7, "Speed": 9}, "Type": ["Special", "Flying"], "Abilities": {"Basic": ["Dancer"], "Advanced": ["Adaptability", "Spinning Dance", "Revelation"], "High": ["Competitive"]}, "Evolution": [[1, "Oricorio", "Null", "Null"]], "Height": 0.6, "SizeClass": "Small", "Weight": 3.4, "BreedingInformation": {"Gender Ratio": 25.0, "Egg Group": ["Flying"], "Average Hatch Rate": 13}, "Diet": ["Herbivore"], "Habitat": ["Beach", "Grassland"], "Capabilities": {"Overland": 5, "Sky": 6, "Swim": 3, "Levitate": 0, "Burrow": 0, "JumpH": 3, "JumpL": 3, "Power": 2, "WeightClass": "1", "Naturewalk": [], "Other": ["Forme Change", "Nectar Dance"]}, "LevelUpMoveList": [{"Level": 1, "Move": "Pound"}, {"Level": 4, "Move": "Growl"}, {"Level": 6, "Move": "Peck"}, {"Level": 10, "Move": "Helping Hand"}, {"Level": 13, "Move": "Air Cutter"}, {"Level": 16, "Move": "Baton Pass"}, {"Level": 20, "Move": "Feather Dance"}, {"Level": 23, "Move": "Double Slap"}, {"Level": 26, "Move": "Teeter Dance"}, {"Level": 30, "Move": "Roost"}, {"Level": 33, "Move": "Captivate"}, {"Level": 36, "Move": "Air Slash"}, {"Level": 40, "Move": "Revelation Dance"}, {"Level": 43, "Move": "Mirror Move"}, {"Level": 46, "Move": "Agility"}, {"Level": 50, "Move": "Hurricane"}], "TMMoveList": ["04", "06", "10", "12", "17", "19", "20", "21", "27", "32", "37", "40", "42", "44", "45", "48", "51", "60", "62", "63", "75", "76", "87", "88", "89", "90", "100"], "EggMoveList": ["Captivate", "Pluck", "Tailwind"], "TutorMoveList": ["Covet", "Defog", "Helping Hand", "Icy Wind", "Pluck", "Role Play", "Sky Attack", "Snore", "Tailwind"], "Skills": {"Athletics": {"Dice": 3, "Mod": 0}, "Acrobatics": {"Dice": 4, "Mod": 1}, "Combat": {"Dice": 3, "Mod": 0}, "Stealth": {"Dice": 3, "Mod": 0}, "Perception": {"Dice": 4, "Mod": 0}, "Focus": {"Dice": 4, "Mod": 2}}}