{"_id": "PACHIRISU", "number": "417", "ptuNumber": 675, "BaseStats": {"HP": 6, "Attack": 5, "Defense": 7, "Special Attack": 5, "Special Defense": 9, "Speed": 10}, "Type": ["Electric", "null"], "Abilities": {"Basic": ["Run Away", "Pickup"], "Advanced": ["Sprint", "Decoy"], "High": ["Volt Absorb"]}, "Evolution": [[1, "Pachirisu", "Null", "Null"]], "Height": 0.4, "SizeClass": "Small", "Weight": 3.9, "BreedingInformation": {"Gender Ratio": 50.0, "Egg Group": ["Field", "Fairy"], "Average Hatch Rate": 4}, "Diet": ["Herbivore"], "Habitat": ["Forest", "Urban"], "Capabilities": {"Overland": 5, "Sky": 0, "Swim": 3, "Levitate": 0, "Burrow": 0, "JumpH": 1, "JumpL": 2, "Power": 1, "WeightClass": "1", "Naturewalk": ["Forest", "Urban"], "Other": ["Underdog", "Zapper"]}, "LevelUpMoveList": [{"Level": 1, "Move": "Bide"}, {"Level": 1, "Move": "Growl"}, {"Level": 5, "Move": "Quick Attack"}, {"Level": 9, "Move": "Charm"}, {"Level": 13, "Move": "Spark"}, {"Level": 17, "Move": "Endure"}, {"Level": 19, "Move": "Nuzzle"}, {"Level": 21, "Move": "Swift"}, {"Level": 25, "Move": "Electro Ball"}, {"Level": 29, "Move": "Sweet Kiss"}, {"Level": 33, "Move": "Thunder Wave"}, {"Level": 37, "Move": "Super Fang"}, {"Level": 41, "Move": "Discharge"}, {"Level": 45, "Move": "Last Resort"}, {"Level": 49, "Move": "Hyper Fang"}], "TMMoveList": ["06", "10", "16", "17", "18", "21", "24", "25", "27", "32", "42", "44", "45", "48", "49", "56", "57", "72", "73", "86", "87", "88", "89", "90", "100"], "EggMoveList": ["Baby-Doll Eyes", "Bestow", "Bite", "Charge", "Covet", "Defense Curl", "Fake Tears", "Flail", "Flatter", "Follow Me", "Ion Deluge", "Iron Tail", "Rollout", "Tail Whip"], "TutorMoveList": ["Covet", "Defense Curl", "Electroweb", "Gunk Shot", "Helping Hand", "Iron Tail", "Laser Focus", "Last Resort", "Magnet Rise", "Mud-Slap", "Rollout", "Seed Bomb", "Shock Wave", "Snore", "Super Fang", "Swift", "Thunder Punch", "Uproar"], "Skills": {"Athletics": {"Dice": 4, "Mod": 2}, "Acrobatics": {"Dice": 3, "Mod": 3}, "Combat": {"Dice": 2, "Mod": 1}, "Stealth": {"Dice": 4, "Mod": 4}, "Perception": {"Dice": 2, "Mod": 1}, "Focus": {"Dice": 2, "Mod": 2}}}