{"_id": "RHYPERIOR", "number": "464", "ptuNumber": 175, "BaseStats": {"HP": 12, "Attack": 14, "Defense": 13, "Special Attack": 6, "Special Defense": 6, "Speed": 4}, "Type": ["Ground", "Rock"], "Abilities": {"Basic": ["Rock Head", "Solid Rock"], "Advanced": ["Sturdy", "Reckless"], "High": ["Lightning Rod"]}, "Evolution": [[1, "Rhyhorn", "Null", "Null"], [2, "Rhydon", 25, "Null"], [3, "Rhyperior", 45, "Null"]], "Height": 2.4, "SizeClass": "Large", "Weight": 120.0, "BreedingInformation": {"Gender Ratio": 50.0, "Egg Group": ["Monster", "Field"], "Average Hatch Rate": -1}, "Diet": ["Herbivore"], "Habitat": ["Mountain"], "Capabilities": {"Overland": 5, "Sky": 0, "Swim": 2, "Levitate": 0, "Burrow": 0, "JumpH": 1, "JumpL": 2, "Power": 11, "WeightClass": "5", "Naturewalk": ["Mountain"], "Other": ["Groundshaper", "Mountable 1", "Tracker"]}, "LevelUpMoveList": [{"Level": 5, "Move": "Fury Attack"}, {"Level": 9, "Move": "Scary Face"}, {"Level": 13, "Move": "Smack Down"}, {"Level": 17, "Move": "Stomp"}, {"Level": 21, "Move": "Bulldoze"}, {"Level": 25, "Move": "Chip Away"}, {"Level": 29, "Move": "Rock Blast"}, {"Level": 33, "Move": "Drill Run"}, {"Level": 37, "Move": "Take Down"}, {"Level": 41, "Move": "Stone Edge"}, {"Level": 48, "Move": "Earthquake"}, {"Level": 55, "Move": "Megahorn"}, {"Level": 62, "Move": "Horn Drill"}, {"Level": 69, "Move": "Rock Wrecker"}], "TMMoveList": ["05", "06", "10", "11", "13", "14", "15", "17", "18", "21", "23", "24", "25", "26", "27", "31", "32", "35", "37", "38", "39", "42", "44", "45", "46", "48", "52", "56", "59", "65", "66", "67", "68", "69", "71", "75", "78", "80", "82", "84", "87", "88", "90", "91", "94", "100"], "EggMoveList": [], "TutorMoveList": ["Ancient Power", "Aqua Tail", "Avalanche", "Block", "Body Slam", "Counter", "Double-Edge", "Dragon Pulse", "Drill Run", "Dynamic Punch", "Earth Power", "Endeavor", "Fire Punch", "Focus Punch", "Fury Cutter", "Hammer Arm (N)", "Horn Drill (N)", "Ice Punch", "Icy Wind", "Iron Head", "Iron Tail", "Mega Kick", "Mega Punch", "Mud-Slap", "Outrage", "Poison Jab (N)", "Rock Wrecker (N)", "Rollout", "Shock Wave", "Seismic Toss", "Snore", "Spite", "Stealth Rock", "Stomping Tantrum", "Superpower", "Thunder Punch", "Uproar"], "Skills": {"Athletics": {"Dice": 5, "Mod": 3}, "Acrobatics": {"Dice": 2, "Mod": 0}, "Combat": {"Dice": 5, "Mod": 0}, "Stealth": {"Dice": 2, "Mod": 0}, "Perception": {"Dice": 3, "Mod": 2}, "Focus": {"Dice": 4, "Mod": 1}}}