{"_id": "SEAKING", "number": "119", "ptuNumber": 614, "Base Stats": {"HP": 8, "Attack": 9, "Defense": 7, "Special Attack": 7, "Special Defense": 8, "Speed": 7}, "Type": ["Water", "null"], "Abilities": {"Basic": ["Lightning Rod", "Water Veil"], "Advanced": ["Dry Skin", "Swift Swim"], "High": ["Refreshing Veil"]}, "Evolution": [[1, "Goldeen", "Null", "Null"], [2, "Seaking", 30, "Null"]], "Height": 1.3, "Size Class": "Medium", "Weight": 39.0, "Breeding Information": {"Gender Ratio": 50.0, "Egg Group": ["Water 2"], "Average Hatch Rate": -1}, "Diet": ["Omnivore"], "Habitat": ["Freshwater"], "Capabilities": {"Overland": 1, "Sky": 0, "Swim": 6, "Levitate": 0, "Burrow": 0, "JumpH": 3, "JumpL": 3, "Power": 3, "WeightClass": "3", "Naturewalk": ["Ocean"], "Other": ["Fountain", "Gilled"]}, "Level Up Move List": [{"Level": 5, "Move": "Supersonic"}, {"Level": 8, "Move": "Horn Attack"}, {"Level": 13, "Move": "Flail"}, {"Level": 16, "Move": "Water Pulse"}, {"Level": 21, "Move": "Aqua Ring"}, {"Level": 24, "Move": "Fury Attack"}, {"Level": 29, "Move": "Agility"}, {"Level": 32, "Move": "Waterfall"}, {"Level": 40, "Move": "Horn Drill"}, {"Level": 46, "Move": "Soak"}, {"Level": 54, "Move": "Megahorn"}], "TM Move List": ["06", "07", "10", "13", "14", "15", "17", "18", "21", "27", "32", "42", "44", "45", "48", "55", "67", "68", "84", "87", "88", "90", "94", "98", "100"], "Egg Move List": [], "Tutor Move List": ["Aqua Ring", "Aqua Tail", "Bounce", "Dive", "Double-Edge", "Drill Run", "Fury Cutter", "Icy Wind", "Knock Off", "Megahorn (N)", "Mud-Slap", "Poison Jab (N)", "Signal Beam", "Snore", "Swift", "Throat Chop", "Water Pulse"], "Skills": {"Athletics": {"Dice": 4, "Mod": 0}, "Acrobatics": {"Dice": 3, "Mod": 1}, "Combat": {"Dice": 3, "Mod": 1}, "Stealth": {"Dice": 2, "Mod": 0}, "Perception": {"Dice": 2, "Mod": 0}, "Focus": {"Dice": 3, "Mod": 0}}}