{"_id": "SILVALLY", "number": "773", "ptuNumber": 917, "Base Stats": {"HP": 10, "Attack": 10, "Defense": 10, "Special Attack": 10, "Special Defense": 10, "Speed": 10}, "Type": ["Normal", "null"], "Abilities": {"Basic": ["RKS System"], "Advanced": ["Adaptability", "Strong Jaw", "Trinity"], "High": ["Download"]}, "Evolution": [[1, "Type: Null", "Null", "Null"], [2, "Silvally", 30, "Null"]], "Height": 2.3, "Size Class": "Large", "Weight": 100.5, "Breeding Information": {"Gender Ratio": -1, "Egg Group": ["None"], "Average Hatch Rate": -1}, "Diet": ["Omnivore"], "Habitat": ["Urban"], "Capabilities": {"Overland": 8, "Sky": 0, "Swim": 4, "Levitate": 0, "Burrow": 0, "JumpH": 1, "JumpL": 1, "Power": 8, "WeightClass": "5", "Naturewalk": [], "Other": ["Mountable 1", "Tracker"]}, "Level Up Move List": [{"Level": "Evo", "Move": "Multi-Attack"}, {"Level": 3, "Move": "Rage"}, {"Level": 5, "Move": "Pursuit"}, {"Level": 8, "Move": "Bite"}, {"Level": 10, "Move": "Aerial Ace"}, {"Level": 13, "Move": "Crush Claw"}, {"Level": 15, "Move": "Scary Face"}, {"Level": 18, "Move": "X-Scissor"}, {"Level": 20, "Move": "Take Down"}, {"Level": 23, "Move": "Metal Sound"}, {"Level": 25, "Move": "Crunch"}, {"Level": 28, "Move": "Double Hit"}, {"Level": 30, "Move": "Air Slash"}, {"Level": 33, "Move": "Punishment"}, {"Level": 35, "Move": "Razor Wind"}, {"Level": 38, "Move": "Tri Attack"}, {"Level": 40, "Move": "Double-Edge"}, {"Level": 43, "Move": "Parting Shot"}], "TM Move List": ["01", "02", "05", "06", "07", "10", "11", "13", "15", "17", "18", "21", "24", "27", "30", "32", "35", "37", "40", "42", "43", "44", "45", "48", "51", "64", "65", "66", "68", "73", "75", "80", "81", "87", "88", "89", "90", "91", "94", "95", "100"], "Egg Move List": [], "Tutor Move List": ["Defog", "Double-Edge", "Draco Meteor", "Fire Fang (N)", "Fire Pledge", "Grass Pledge", "Heal Block (N)", "Heat Wave", "Hyper Voice", "Ice Fang (N)", "Icy Wind", "Imprison (N)", "Iron Defense", "Iron Head (N)", "Laser Focus", "Last Resort", "Magic Coat", "Outrage", "Poison Fang (N)", "Signal Beam", "Snore", "Tailwind", "Thunder Fang (N)", "Water Pledge", "Zen Headbutt"], "Skills": {"Athletics": {"Dice": 5, "Mod": 1}, "Acrobatics": {"Dice": 3, "Mod": 0}, "Combat": {"Dice": 5, "Mod": 1}, "Stealth": {"Dice": 2, "Mod": 0}, "Perception": {"Dice": 5, "Mod": 1}, "Focus": {"Dice": 4, "Mod": 0}}}