{"_id": "SUICUNE", "number": "245", "ptuNumber": 855, "BaseStats": {"HP": 10, "Attack": 8, "Defense": 12, "Special Attack": 9, "Special Defense": 12, "Speed": 9}, "Type": ["Water", "null"], "Abilities": {"Basic": ["Pressure", "Inner Focus"], "Advanced": ["Sprint", "Run Away"], "High": ["Speed Boost"]}, "Evolution": [[1, "Suicune", "Null", "Null"]], "Height": 2.0, "SizeClass": "Large", "Weight": 187.0, "BreedingInformation": {"Gender Ratio": -1, "Egg Group": ["None"], "Average Hatch Rate": 40}, "Diet": ["Omnivore"], "Habitat": ["Grassland"], "Capabilities": {"Overland": 10, "Sky": 0, "Swim": 10, "Levitate": 0, "Burrow": 0, "JumpH": 3, "JumpL": 3, "Power": 8, "WeightClass": "5", "Naturewalk": ["Grassland", "Wetlands"], "Other": ["Fountain", "Guster", "Mountable 2", "Tracker"]}, "LevelUpMoveList": [{"Level": 1, "Move": "Bite"}, {"Level": 1, "Move": "Leer"}, {"Level": 4, "Move": "Bubble Beam"}, {"Level": 8, "Move": "Rain Dance"}, {"Level": 11, "Move": "Gust"}, {"Level": 15, "Move": "Aurora Beam"}, {"Level": 18, "Move": "Mist"}, {"Level": 22, "Move": "Mirror Coat"}, {"Level": 25, "Move": "Ice Fang"}, {"Level": 29, "Move": "Tailwind"}, {"Level": 32, "Move": "Extrasensory"}, {"Level": 36, "Move": "Hydro Pump"}, {"Level": 39, "Move": "Calm Mind"}, {"Level": 43, "Move": "Blizzard"}], "TMMoveList": ["04", "05", "06", "07", "10", "11", "13", "14", "15", "17", "18", "21", "27", "30", "32", "33", "37", "42", "44", "48", "55", "60", "68", "77", "78", "87", "88", "90", "94", "95", "98", "100"], "EggMoveList": [], "TutorMoveList": ["Aqua Ring", "Avalanche", "Body Slam", "Brine", "Dive", "Double-Edge", "Icy Wind", "Iron Head", "Iron Tail", "Laser Focus", "Mud-Slap", "Ominous Wind", "Sheer Cold (N)", "Signal Beam", "Snore", "Swift", "Tailwind", "Water Pulse", "Whirlpool"], "Skills": {"Athletics": {"Dice": 4, "Mod": 2}, "Acrobatics": {"Dice": 4, "Mod": 2}, "Combat": {"Dice": 4, "Mod": 0}, "Stealth": {"Dice": 4, "Mod": 0}, "Perception": {"Dice": 3, "Mod": 2}, "Focus": {"Dice": 5, "Mod": 2}}}