{"_id": "TYRUNT", "number": "696", "ptuNumber": 812, "Base Stats": {"HP": 6, "Attack": 9, "Defense": 8, "Special Attack": 5, "Special Defense": 5, "Speed": 5}, "Type": ["Rock", "Dragon"], "Abilities": {"Basic": ["Sprint", "Hyper Cutter"], "Advanced": ["Rock Head", "Strong Jaw"], "High": ["Moxie"]}, "Evolution": [[1, "Tyrunt", "Null", "Null"], [2, "Tyrantrum", 30, "Null"]], "Height": 0.8, "Size Class": "Small", "Weight": 26.0, "Breeding Information": {"Gender Ratio": 87.5, "Egg Group": ["Monster", "Dragon"], "Average Hatch Rate": 16}, "Diet": ["Carnivore"], "Habitat": ["Cave", "Mountain"], "Capabilities": {"Overland": 4, "Sky": 0, "Swim": 3, "Levitate": 0, "Burrow": 0, "JumpH": 1, "JumpL": 1, "Power": 3, "WeightClass": "3", "Naturewalk": ["Mountain"], "Other": ["Underdog"]}, "Level Up Move List": [{"Level": 1, "Move": "Tackle"}, {"Level": 1, "Move": "Tail Whip"}, {"Level": 6, "Move": "Roar"}, {"Level": 10, "Move": "Stomp"}, {"Level": 12, "Move": "Bide"}, {"Level": 15, "Move": "Stealth Rock"}, {"Level": 17, "Move": "Bite"}, {"Level": 20, "Move": "Charm"}, {"Level": 26, "Move": "Ancient Power"}, {"Level": 30, "Move": "Dragon Tail"}, {"Level": 34, "Move": "Crunch"}, {"Level": 37, "Move": "Dragon Claw"}, {"Level": 40, "Move": "Thrash"}, {"Level": 44, "Move": "Earthquake"}, {"Level": 49, "Move": "Horn Drill"}], "TM Move List": ["02", "05", "06", "10", "11", "17", "21", "26", "27", "31", "32", "37", "39", "40", "42", "44", "45", "48", "69", "71", "78", "80", "82", "87", "88", "90", "97", "100"], "Egg Move List": ["Curse", "Dragon Dance", "Fire Fang", "Ice Fang", "Poison Fang", "Thunder Fang"], "Tutor Move List": ["Ancient Power", "Block", "Draco Meteor", "Dragon Pulse", "Earth Power", "Hyper Voice", "Iron Defense", "Iron Head", "Iron Tail", "Outrage", "Snore", "Stealth Rock", "Stomping Tantrum", "Superpower", "Zen Headbutt"], "Skills": {"Athletics": {"Dice": 3, "Mod": 0}, "Acrobatics": {"Dice": 3, "Mod": 0}, "Combat": {"Dice": 3, "Mod": 2}, "Stealth": {"Dice": 2, "Mod": 0}, "Perception": {"Dice": 2, "Mod": 0}, "Focus": {"Dice": 1, "Mod": 0}}}